AutoClassifier/Training.py
AutoClassifier/__init__.py
AutoClassifier/main.py
AutoClassifier/predict.py
AutoClassifier/com_utils/__init__.py
AutoClassifier/com_utils/utils.py
AutoClassifier/utils/__init__.py
AutoClassifier/utils/close_match.py
AutoClassifier/utils/config.py
AutoClassifier/utils/data_management.py
AutoClassifier/utils/input.py
AutoClassifier/utils/model.py
AutoClassifier/utils/model_config.py
AutoClassifier-0.0.3.dist-info/LICENSE
AutoClassifier-0.0.3.dist-info/METADATA
AutoClassifier-0.0.3.dist-info/WHEEL
AutoClassifier-0.0.3.dist-info/entry_points.txt
AutoClassifier-0.0.3.dist-info/top_level.txt
AutoClassifier-0.0.3.dist-info/RECORD
