Metadata-Version: 2.1
Name: AutoClassifier
Version: 0.0.3
Summary: Automatic Image classification 
Home-page: https://github.com/sarikamohan08/AutoClassifier
Author: Sarika Mohanraj
Author-email: sarikamohan08@gmail.com
License: MIT
Keywords: AutoClassifier
Platform: UNKNOWN
Classifier: Development Status :: 3 - Alpha
Classifier: Intended Audience :: Developers
Classifier: Topic :: Software Development :: Build Tools
Classifier: License :: OSI Approved :: MIT License
Classifier: Programming Language :: Python :: 3
Classifier: Programming Language :: Python :: 3.4
Classifier: Programming Language :: Python :: 3.5
Classifier: Programming Language :: Python :: 3.6
License-File: LICENSE
Requires-Dist: tensorflow (==2.4.1)
Requires-Dist: scipy (==1.3.0)
Requires-Dist: numpy
Requires-Dist: pandas
Requires-Dist: Pillow (==8.3.2)
Requires-Dist: Flask
Requires-Dist: Flask-Cors (==3.0.10)
